python/C000_commands_generated.py
python/EMPT_empty_generated.py
python/FILE_ID_LIST.py
python/M100_mission_generated.py
python/R000_states_generated.py
python/R001_states_drone1d_generated.py
python/S000_srv_resetallmsg_generated.py
python/S001_srv_globalparamsmsg_generated.py
python/S002_srv_wsparamsmsg_generated.py
python/S003_srv_simparamsmsg_generated.py
python/S004_srv_omrwallmsg_generated.py
python/S005_srv_drone1dpidmsg_generated.py
python/S006_srv_imureplaymsg_generated.py
python/S007_srv_vrobotphysicalpropertymsg_generated.py
python/VROBOTS_CMDS.py
python/__init__.py
python/collision_generated.py
python/states_msg_helper.py
ubicoders-vrobots-msgs/C000_commands_generated.py
ubicoders-vrobots-msgs/EMPT_empty_generated.py
ubicoders-vrobots-msgs/FILE_ID_LIST.py
ubicoders-vrobots-msgs/M100_mission_generated.py
ubicoders-vrobots-msgs/R000_states_generated.py
ubicoders-vrobots-msgs/R001_states_drone1d_generated.py
ubicoders-vrobots-msgs/S000_srv_resetallmsg_generated.py
ubicoders-vrobots-msgs/S001_srv_globalparamsmsg_generated.py
ubicoders-vrobots-msgs/S002_srv_wsparamsmsg_generated.py
ubicoders-vrobots-msgs/S003_srv_simparamsmsg_generated.py
ubicoders-vrobots-msgs/S004_srv_omrwallmsg_generated.py
ubicoders-vrobots-msgs/S005_srv_drone1dpidmsg_generated.py
ubicoders-vrobots-msgs/S006_srv_imureplaymsg_generated.py
ubicoders-vrobots-msgs/S007_srv_vrobotphysicalpropertymsg_generated.py
ubicoders-vrobots-msgs/VROBOTS_CMDS.py
ubicoders-vrobots-msgs/__init__.py
ubicoders-vrobots-msgs/collision_generated.py
ubicoders-vrobots-msgs/states_msg_helper.py
ubicoders_vrobots_msgs/C000_commands_generated.py
ubicoders_vrobots_msgs/EMPT_empty_generated.py
ubicoders_vrobots_msgs/FILE_ID_LIST.py
ubicoders_vrobots_msgs/M100_mission_generated.py
ubicoders_vrobots_msgs/R000_states_generated.py
ubicoders_vrobots_msgs/R001_states_drone1d_generated.py
ubicoders_vrobots_msgs/S000_srv_resetallmsg_generated.py
ubicoders_vrobots_msgs/S001_srv_globalparamsmsg_generated.py
ubicoders_vrobots_msgs-2.0.2.dist-info/licenses/LICENSE
ubicoders_vrobots_msgs-2.0.2.dist-info/METADATA
ubicoders_vrobots_msgs-2.0.2.dist-info/WHEEL
ubicoders_vrobots_msgs-2.0.2.dist-info/top_level.txt
ubicoders_vrobots_msgs-2.0.2.dist-info/RECORD
